mappgene/__init__.py
mappgene/cli.py
mappgene/data/container/build.sh
mappgene/data/container/recipe.def
mappgene/data/example_inputs/example_MN908947_3_1_R1.fastq.gz
mappgene/data/example_inputs/example_MN908947_3_1_R2.fastq.gz
mappgene/data/extra_files/ivar/GCF_009858895.2_ASM985889v3_genomic.gff
mappgene/data/extra_files/ivar/KJ776791.2.gff3
mappgene/data/extra_files/ivar/KU501215.1.gff3
mappgene/data/extra_files/ivar/KU955593.1.gff3
mappgene/data/extra_files/ivar/KX087101.3.gff3
mappgene/data/extra_files/ivar/Primers for amplicon-based sequencing - ZIKV - Asia_America - 400bp.tsv
mappgene/data/extra_files/ivar/map_zibra_primers.sh
mappgene/data/extra_files/ivar/zibra.fa
mappgene/data/extra_files/ivar/primers_1200bp/nCoV-2019.bed
mappgene/data/extra_files/ivar/primers_1200bp/nCoV-2019.reference.fasta
mappgene/data/extra_files/ivar/primers_1200bp/nCoV-2019.reference.fasta.fai
mappgene/data/extra_files/ivar/primers_1200bp/nCoV-2019.scheme.bed
mappgene/data/extra_files/ivar/primers_1200bp/nCoV-2019.tsv
mappgene/data/extra_files/ivar/primers_400bp/nCoV-2019.bed
mappgene/data/extra_files/ivar/primers_400bp/nCoV-2019.insert.bed
mappgene/data/extra_files/ivar/primers_400bp/nCoV-2019.primer.bed
mappgene/data/extra_files/ivar/primers_400bp/nCoV-2019.reference.fasta
mappgene/data/extra_files/ivar/primers_400bp/nCoV-2019.scheme.bed
mappgene/data/extra_files/ivar/primers_400bp/nCoV-2019.tsv
mappgene/data/extra_files/ivar/primers_combo_3_4.1bp/MAPPGENE_README
mappgene/data/extra_files/ivar/primers_combo_3_4.1bp/nCoV-2019.bed
mappgene/data/extra_files/ivar/primers_combo_3_4.1bp/nCoV-2019.scheme.bed
mappgene/data/extra_files/ivar/primers_combo_3_4.1bp/nCoV-2019.tsv
mappgene/data/extra_files/ivar/primers_combo_3_4.1bp/rename_file_for_mappgene.sh
mappgene/data/extra_files/ivar/primers_v4.1bp/MAPPGENE_README
mappgene/data/extra_files/ivar/primers_v4.1bp/README
mappgene/data/extra_files/ivar/primers_v4.1bp/SARS-CoV-2.insert.bed
mappgene-1.4.0.dist-info/LICENSE
mappgene-1.4.0.dist-info/METADATA
mappgene-1.4.0.dist-info/NOTICE
mappgene-1.4.0.dist-info/WHEEL
mappgene-1.4.0.dist-info/entry_points.txt
mappgene-1.4.0.dist-info/top_level.txt
mappgene-1.4.0.dist-info/RECORD
